mpservice/__init__.py
mpservice/_common.py
mpservice/_http.py
mpservice/_queues.py
mpservice/background_task.py
mpservice/http.py
mpservice/pipe.py
mpservice/py.typed
mpservice/queue.py
mpservice/socket.py
mpservice/asyncio/__init__.py
mpservice/concurrent/__init__.py
mpservice/concurrent/futures/__init__.py
mpservice/mpserver/__init__.py
mpservice/mpserver/_server.py
mpservice/mpserver/_servlet.py
mpservice/mpserver/_worker.py
mpservice/multiprocessing/__init__.py
mpservice/multiprocessing/context.py
mpservice/multiprocessing/managers.py
mpservice/multiprocessing/pool.py
mpservice/multiprocessing/queues.py
mpservice/multiprocessing/remote_exception.py
mpservice/multiprocessing/runner.py
mpservice/multiprocessing/server_process.py
mpservice/multiprocessing/synchronize.py
mpservice/streamer/__init__.py
mpservice/streamer/_iterable_queue.py
mpservice/streamer/_streamer.py
mpservice/streamer/_streamer_async.py
mpservice/streamer/_tee.py
mpservice/threading/__init__.py
mpservice-0.16.8.dist-info/LICENSE
mpservice-0.16.8.dist-info/WHEEL
mpservice-0.16.8.dist-info/METADATA
mpservice-0.16.8.dist-info/RECORD
