Metadata-Version: 2.3
Name: mpservice
Version: 0.16.8
Summary: The package `mpservice <https://github.com/zpz/mpservice>`_ provides utilities for Python concurrency, including most notably
Author-email: Zepu Zhang <zepu.zhang@gmail.com>
Requires-Python: >=3.10
Classifier: Intended Audience :: Developers
Classifier: Programming Language :: Python :: 3
Classifier: Topic :: Software Development :: Libraries :: Python Modules
Requires-Dist: asyncstdlib
Requires-Dist: deprecation
Requires-Dist: psutil
Requires-Dist: typing-extensions
Requires-Dist: uvicorn[standard] >=0.30.0,<1.0
Requires-Dist: sphinx ; extra == "doc"
Requires-Dist: numpydoc ; extra == "doc"
Requires-Dist: pydata-sphinx-theme ; extra == "doc"
Requires-Dist: coverage[toml] ; extra == "test"
Requires-Dist: Faker ; extra == "test"
Requires-Dist: httpx ; extra == "test"
Requires-Dist: pytest ; extra == "test"
Requires-Dist: pytest-asyncio ; extra == "test"
Requires-Dist: requests ; extra == "test"
Requires-Dist: starlette ; extra == "test"
Requires-Dist: zpz ; extra == "test"
Project-URL: Source, https://github.com/zpz/mpservice
Provides-Extra: doc
Provides-Extra: test
